[
  {"id":"nr-001","target":15,"start":0,"slots":3,"difficulty":1,"description":"Benny needs 15 berries for breakfast","availableOps":[{"type":"+","value":7,"display":"+7"},{"type":"+","value":8,"display":"+8"},{"type":"+","value":5,"display":"+5"},{"type":"-","value":2,"display":"-2"}]},
  {"id":"nr-002","target":20,"slots":3,"difficulty":1,"availableOps":[{"type":"+","value":10,"display":"+10"},{"type":"+","value":6,"display":"+6"},{"type":"+","value":4,"display":"+4"},{"type":"-","value":3,"display":"-3"}]},
  {"id":"nr-003","target":12,"slots":3,"difficulty":1,"availableOps":[{"type":"+","value":9,"display":"+9"},{"type":"+","value":5,"display":"+5"},{"type":"-","value":2,"display":"-2"},{"type":"+","value":3,"display":"+3"}]},
  {"id":"nr-004","target":30,"slots":3,"difficulty":1,"description":"Three logs to reach island 30","availableOps":[{"type":"+","value":15,"display":"+15"},{"type":"+","value":10,"display":"+10"},{"type":"+","value":5,"display":"+5"},{"type":"+","value":12,"display":"+12"}]},
  {"id":"nr-005","target":25,"slots":3,"difficulty":1,"availableOps":[{"type":"+","value":20,"display":"+20"},{"type":"+","value":8,"display":"+8"},{"type":"-","value":3,"display":"-3"},{"type":"+","value":7,"display":"+7"}]},
  {"id":"nr-006","target":18,"slots":3,"difficulty":1,"availableOps":[{"type":"+","value":10,"display":"+10"},{"type":"+","value":9,"display":"+9"},{"type":"-","value":1,"display":"-1"},{"type":"+","value":4,"display":"+4"}]},
  {"id":"nr-007","target":40,"slots":3,"difficulty":1,"description":"Collect 40 acorns","availableOps":[{"type":"+","value":20,"display":"+20"},{"type":"+","value":15,"display":"+15"},{"type":"+","value":10,"display":"+10"},{"type":"+","value":5,"display":"+5"}]},
  {"id":"nr-008","target":50,"slots":3,"difficulty":1,"availableOps":[{"type":"+","value":30,"display":"+30"},{"type":"+","value":25,"display":"+25"},{"type":"-","value":5,"display":"-5"},{"type":"+","value":20,"display":"+20"}]},
  {"id":"nr-009","target":100,"slots":3,"difficulty":1,"description":"Century crossing","availableOps":[{"type":"+","value":60,"display":"+60"},{"type":"+","value":50,"display":"+50"},{"type":"-","value":10,"display":"-10"},{"type":"+","value":40,"display":"+40"}]},
  {"id":"nr-010","target":75,"slots":3,"difficulty":1,"availableOps":[{"type":"+","value":50,"display":"+50"},{"type":"+","value":30,"display":"+30"},{"type":"-","value":5,"display":"-5"},{"type":"+","value":25,"display":"+25"}]},

  {"id":"nr-101","target":48,"slots":4,"difficulty":2,"description":"Use times tables to cross faster","availableOps":[{"type":"×","value":2,"display":"×2"},{"type":"+","value":20,"display":"+20"},{"type":"+","value":4,"display":"+4"},{"type":"×","value":3,"display":"×3"},{"type":"-","value":6,"display":"-6"}]},
  {"id":"nr-102","target":60,"slots":4,"difficulty":2,"availableOps":[{"type":"+","value":30,"display":"+30"},{"type":"×","value":2,"display":"×2"},{"type":"-","value":5,"display":"-5"},{"type":"+","value":15,"display":"+15"},{"type":"÷","value":2,"display":"÷2"}]},
  {"id":"nr-103","target":36,"slots":4,"difficulty":2,"availableOps":[{"type":"+","value":12,"display":"+12"},{"type":"×","value":3,"display":"×3"},{"type":"-","value":4,"display":"-4"},{"type":"+","value":8,"display":"+8"},{"type":"÷","value":2,"display":"÷2"}]},
  {"id":"nr-104","target":72,"slots":4,"difficulty":2,"availableOps":[{"type":"+","value":40,"display":"+40"},{"type":"×","value":2,"display":"×2"},{"type":"-","value":8,"display":"-8"},{"type":"+","value":12,"display":"+12"},{"type":"÷","value":3,"display":"÷3"}]},
  {"id":"nr-105","target":100,"slots":4,"difficulty":2,"availableOps":[{"type":"+","value":50,"display":"+50"},{"type":"×","value":2,"display":"×2"},{"type":"-","value":10,"display":"-10"},{"type":"+","value":25,"display":"+25"},{"type":"÷","value":5,"display":"÷5"}]},
  {"id":"nr-106","target":32,"slots":4,"difficulty":2,"description":"Four times table practice","availableOps":[{"type":"+","value":16,"display":"+16"},{"type":"×","value":2,"display":"×2"},{"type":"+","value":8,"display":"+8"},{"type":"×","value":4,"display":"×4"},{"type":"-","value":4,"display":"-4"}]},
  {"id":"nr-107","target":56,"slots":4,"difficulty":2,"availableOps":[{"type":"+","value":28,"display":"+28"},{"type":"×","value":2,"display":"×2"},{"type":"+","value":14,"display":"+14"},{"type":"×","value":4,"display":"×4"},{"type":"÷","value":2,"display":"÷2"}]},
  {"id":"nr-108","target":81,"slots":4,"difficulty":2,"description":"Three times table to 81","availableOps":[{"type":"+","value":27,"display":"+27"},{"type":"×","value":3,"display":"×3"},{"type":"+","value":54,"display":"+54"},{"type":"÷","value":3,"display":"÷3"},{"type":"+","value":9,"display":"+9"}]},
  {"id":"nr-109","target":96,"slots":4,"difficulty":2,"availableOps":[{"type":"+","value":48,"display":"+48"},{"type":"×","value":2,"display":"×2"},{"type":"+","value":24,"display":"+24"},{"type":"×","value":4,"display":"×4"},{"type":"-","value":12,"display":"-12"}]},
  {"id":"nr-110","target":120,"slots":4,"difficulty":2,"description":"Eight times table challenge","availableOps":[{"type":"+","value":60,"display":"+60"},{"type":"×","value":2,"display":"×2"},{"type":"+","value":40,"display":"+40"},{"type":"×","value":3,"display":"×3"},{"type":"÷","value":4,"display":"÷4"}]},

  {"id":"nr-201","target":250,"slots":4,"difficulty":3,"description":"Inventor challenge with brackets hint","availableOps":[{"type":"+","value":100,"display":"+100"},{"type":"×","value":3,"display":"×3"},{"type":"-","value":50,"display":"-50"},{"type":"+","value":75,"display":"+75"},{"type":"÷","value":2,"display":"÷2"},{"type":"×","value":4,"display":"×4"}]},
  {"id":"nr-202","target":360,"slots":5,"difficulty":3,"availableOps":[{"type":"+","value":120,"display":"+120"},{"type":"×","value":3,"display":"×3"},{"type":"-","value":20,"display":"-20"},{"type":"÷","value":2,"display":"÷2"},{"type":"+","value":80,"display":"+80"},{"type":"×","value":2,"display":"×2"}]},
  {"id":"nr-203","target":144,"slots":4,"difficulty":3,"availableOps":[{"type":"+","value":60,"display":"+60"},{"type":"×","value":2,"display":"×2"},{"type":"+","value":24,"display":"+24"},{"type":"÷","value":3,"display":"÷3"},{"type":"×","value":4,"display":"×4"},{"type":"-","value":12,"display":"-12"}]},
  {"id":"nr-204","target":500,"slots":5,"difficulty":3,"availableOps":[{"type":"+","value":200,"display":"+200"},{"type":"×","value":2,"display":"×2"},{"type":"+","value":150,"display":"+150"},{"type":"-","value":50,"display":"-50"},{"type":"÷","value":2,"display":"÷2"},{"type":"+","value":100,"display":"+100"}]},
  {"id":"nr-205","target":720,"slots":5,"difficulty":3,"description":"Six times tables extension","availableOps":[{"type":"+","value":240,"display":"+240"},{"type":"×","value":3,"display":"×3"},{"type":"+","value":120,"display":"+120"},{"type":"×","value":2,"display":"×2"},{"type":"÷","value":3,"display":"÷3"},{"type":"+","value":60,"display":"+60"}]},
  {"id":"nr-206","target":1000,"slots":5,"difficulty":3,"description":"Reach one thousand","availableOps":[{"type":"+","value":500,"display":"+500"},{"type":"×","value":2,"display":"×2"},{"type":"+","value":250,"display":"+250"},{"type":"+","value":200,"display":"+200"},{"type":"-","value":100,"display":"-100"},{"type":"÷","value":2,"display":"÷2"}]},
  {"id":"nr-207","target":640,"slots":5,"difficulty":3,"availableOps":[{"type":"+","value":320,"display":"+320"},{"type":"×","value":2,"display":"×2"},{"type":"+","value":160,"display":"+160"},{"type":"×","value":4,"display":"×4"},{"type":"-","value":80,"display":"-80"},{"type":"÷","value":2,"display":"÷2"}]},
  {"id":"nr-208","target":405,"slots":4,"difficulty":3,"description":"Nine times table stretch","availableOps":[{"type":"+","value":135,"display":"+135"},{"type":"×","value":3,"display":"×3"},{"type":"+","value":270,"display":"+270"},{"type":"÷","value":3,"display":"÷3"},{"type":"+","value":45,"display":"+45"},{"type":"×","value":9,"display":"×9"}]},
  {"id":"nr-209","target":864,"slots":5,"difficulty":3,"availableOps":[{"type":"+","value":288,"display":"+288"},{"type":"×","value":3,"display":"×3"},{"type":"+","value":144,"display":"+144"},{"type":"×","value":2,"display":"×2"},{"type":"÷","value":4,"display":"÷4"},{"type":"+","value":72,"display":"+72"}]},
  {"id":"nr-210","target":999,"slots":5,"difficulty":3,"description":"Almost 1000 challenge","availableOps":[{"type":"+","value":333,"display":"+333"},{"type":"×","value":3,"display":"×3"},{"type":"+","value":111,"display":"+111"},{"type":"×","value":9,"display":"×9"},{"type":"-","value":1,"display":"-1"},{"type":"+","value":222,"display":"+222"}]}
]
